swarmauri_tool_jupyterexportmarkdown/JupyterExportMarkdownTool.py
swarmauri_tool_jupyterexportmarkdown/__init__.py
swarmauri_tool_jupyterexportmarkdown-1.1.5.dist-info/LICENSE
swarmauri_tool_jupyterexportmarkdown-1.1.5.dist-info/METADATA
swarmauri_tool_jupyterexportmarkdown-1.1.5.dist-info/WHEEL
swarmauri_tool_jupyterexportmarkdown-1.1.5.dist-info/entry_points.txt
swarmauri_tool_jupyterexportmarkdown-1.1.5.dist-info/RECORD
